<?xml version="1.0" encoding="UTF-8"?>
<CDM xmlns="http://cdm-fr.fr/2013/CDM" xmlns:xsi="http://www.w3.org/2001/XMLSchema-instance" xmlns:cdmfr="http://cdm-fr.fr/2013/CDM-frSchema" xmlns:xhtml="http://www.w3.org/1999/xhtml" xmlns:utop="http://www.utop.fr/xsd/CDM" xsi:schemaLocation="http://cdm-fr.fr/2013/CDM https://cdm-fr.fr/2013/schemas/CDMFR.xsd" profile="CDM-fr" language="francais">
  <cdmfr:habilitation>
    <cdmfr:partnership>
     <cdmfr:partnerName>
        <cdmfr:text>UNIT</cdmfr:text>
      </cdmfr:partnerName>
      <cdmfr:partnerName>
        <cdmfr:text>UNISCIEL</cdmfr:text>
      </cdmfr:partnerName>
      <cdmfr:partnerName>
        <cdmfr:text>Université de Lille</cdmfr:text>
      </cdmfr:partnerName>
      <cdmfr:partnerName>
        <cdmfr:text>École des Mines de Douai</cdmfr:text>
      </cdmfr:partnerName>
      <cdmfr:partnerName>
        <cdmfr:text>Institut Mines Télécom</cdmfr:text>
      </cdmfr:partnerName>
      <cdmfr:partnershipType partnershipValueSet="Académique"/>
	  <cdmfr:partnershipType partnershipValueSet="National"/>
      <cdmfr:training>
        <cdmfr:trainingStrategy>
          <infoBlock></infoBlock>
        </cdmfr:trainingStrategy>
      </cdmfr:training>
    </cdmfr:partnership>
  </cdmfr:habilitation> 
  <program id="FRUAIxxxxxxxxxxxxxxxxxx">
    <programID>FRUAIxxxxxxxxxxxxxxxxxx</programID>
    <cdmfr:programName>
      <cdmfr:text>MOOC Live Object Programming in Pharo</cdmfr:text>
    </cdmfr:programName>
    <!-- Référentiel RNCP : TEXTE -->
    <cdmfr:programCode codeSet="certifRNCP"></cdmfr:programCode>
    <!-- Référentiel DGESIP : LISTE A CHOIX-->
    <cdmfr:programCode codeSet="sectDGESIP">15000</cdmfr:programCode>
    <cdmfr:programCode libSet="sectDGESIP">Informatique</cdmfr:programCode>
    <!-- Référentiel ERASMUS : LISTE A CHOIX-->
    <cdmfr:programCode codeSet="ERASMUS"></cdmfr:programCode>
    <cdmfr:programCode libSet="ERASMUS"></cdmfr:programCode>
   <!-- Référentiel CITE97 : LISTE A CHOIX -->
    <cdmfr:programCode codeSet="cite97"></cdmfr:programCode>
    <cdmfr:programCode libSet="cite97"></cdmfr:programCode>
     <!-- Référentiel FAP : LISTE A CHOIX -->
    <cdmfr:programCode codeSet="FAP"></cdmfr:programCode>
    <cdmfr:programCode libSet="FAP"></cdmfr:programCode>
    <!-- Référentiel SISE : LISTE A CHOIX-->
    <cdmfr:programCode codeSet="sectDiscipSISE"></cdmfr:programCode>
    <cdmfr:programCode libSet="sectDiscipSISE"></cdmfr:programCode>
    <cdmfr:webLink>
      <href>https://www.fun-mooc.fr/courses/inria/41010/session01/about</href>
      <cdmfr:linkName>Live Object Programming in Pharo</cdmfr:linkName>
    </cdmfr:webLink>
    <!-- Valeur d'attribut = Nature du programme considéré : LISTE A CHOIX -->
    <cdmfr:programDescription nature="">
      <infoBlock>Pharo is a pure object-oriented programming language in the tradition of Smalltalk. It offers a unique developing experience in constant interaction with live objects. Pharo is elegant, fun to use and very powerful. It is very easy to learn and enables to understand advanced concept in a natural way. When programming in Pharo, you are immersed in a world of live objects. You have immediate feedback at any moment of your development on objects representing web applications, code itself, graphics, network…

Pharo is also a very powerful open-source environment used by companies to develop web applications.

In this MOOC, we will present more specifically Pharo’s Web stack which changes the way you build web applications.

In addition we will present fundamental programming concepts and how Pharo uses them. We will present some coding idioms and Design Patterns to better design object-oriented applications. Such concepts can be applied to any object-oriented programming language.
</infoBlock>
    </cdmfr:programDescription>
    <!-- Qualifications visés par la formation : compétences, aptitudes, notes, grades, droit de pratiquer, statut professionnel accordés aux titulaires de la qualification -->
    <qualification>
      <cdmfr:qualificationDescription>
        <infoBlock></infoBlock>
      </cdmfr:qualificationDescription>
      <cdmfr:credits ECTScredits="">
      </cdmfr:credits>
      <!-- Niveau du diplôme décerné par l'établissement après la réussite des études : LISTE A CHOIX -->
      <cdmfr:degree degree=""/>
      <!-- La gestion de l'information concernant les métiers se fait à l'aide de deux champs d'information obligatoire. Le premier permet une description textuelle des métiers visés, le second repose sur le code ROME -->
      <cdmfr:profession>
        <infoBlock></infoBlock>
        <cdmfr:romeData romeCode="" romeLibel=""/>
      </cdmfr:profession>
      <!-- Description des débouchés professionnels et orientations que permet cette formation -->
      <cdmfr:studyQualification>
        <infoBlock></infoBlock>
      </cdmfr:studyQualification>
    </qualification>
    <cdmfr:ppalTeachingLanguage teachingLang="Anglais"/>
    <!-- Niveau d'études de la formation décrite : LISTE A CHOIX -->
    <levelCode codeSet="BAC+4"/>
    <learningObjectives>Throughout this MOOC you will :

-learn how to program in Pharo,
-be immersed in a live environment and live a new programming experience,
-develop a web application to apply the different aspects of Pharo presented in the course.

This MOOC will also provide a new vision of the fundamental principles of object-oriented programming, i.e. polymorphism and late binding.</learningObjectives>
    <admissionInfo> 
    <!-- Valeur d'attribut = Validation des Acquis de l'Experience : BOOLÉEN -->
      <cdmfr:admissionDescription equiv="Non">This course is avalaible to everybody.</cdmfr:admissionDescription>
      <studentPlaces>None. This course is open to everyone. </studentPlaces>
      <teachingStart date="2016-05-02"/>
      <registrationDeadline date=""/>
     </admissionInfo>
    <formalPrerequisites>
      <infoBlock>A first experience in object-oriented programming is better.</infoBlock>
    </formalPrerequisites>
    <!-- Lieu(x) de la formation en présence -->
    <cdmfr:teachingPlace>
      <cdmfr:CDMlocation>
        <infoBlock>Online</infoBlock>
      </cdmfr:CDMlocation>
    </cdmfr:teachingPlace>
    <targetGroup>Bachelor students, Master students, engineers...</targetGroup>
    <!-- Forme proposée pour les enseignements et/ou description des modalités de la formation : BOOLÉEN ou LISTE A CHOIX-->
    <formOfTeaching org="formInit" method="Non"/>
    <formOfTeaching org="formCont" method="Non"/>
    <formOfTeaching org="formAppr" method="Non"/>
    <formOfTeaching org="formPro" method="Non"/>
    <formOfTeaching org="formDist" method="Obligatoire"/>
    <formOfAssessment>
      <infoBlock>At the end of the course, an attestation of achievement will be delivered to the participants who will have obtained the minimal score required. The evaluation is based on the quizzes which have to be done each week.
</infoBlock>
    </formOfAssessment>
    <programDuration>7 weeks</programDuration>
    <!-- Décrit comment la formation est structurée et de quels enseignements elle est composée-->
    <cdmfr:programStructure>
<infoBlock>Course syllabus
Week 1 : Welcome on Board and Syntax Discovery
Week 2 : Pharo Syntax, Blocks and Inspector
Week 3 : Design, Class Methods and Collections
Week 4 : Inheritance and Lookup and Web Development
Week 5 : Exception, Debugging and Reflection
Week 6 : Rethink Lookup and Advanced Object-Oriented Design
</infoBlock>
    </cdmfr:programStructure>
    <expenses>free</expenses>
    <contacts>
      <infoBlock>utop@inria.fr</infoBlock>
      <infoBlock>contact-mooclab@inria.fr</infoBlock>
     </contacts>
    <infoBlock></infoBlock>
    <searchword>MOOC</searchword>
    <searchword>Pharo</searchword>
    <searchword>web application</searchword>
    <searchword>object-oriented programmation</searchword>
    <searchword>language programmation</searchword>
  </program>
  <orgUnit>
    <orgUnitName>
      <text>Institut national de recherche en informatique et en automatique</text>
    </orgUnitName>
    <cdmfr:orgUnitSecondName>
      <cdmfr:secondName>INRIA</cdmfr:secondName>
    </cdmfr:orgUnitSecondName>
  </orgUnit>
  <utop:utop>
    <utop:dateEdition date="2016-22-09"/>
    <utop:utopTag>home-example</utop:utopTag>
    <utop:utopTag>utop-cofinance</utop:utopTag>
  </utop:utop>
</CDM>